MutSeq/MutSeq.py
MutSeq/__init__.py
MutSeq/__main__.py
MutSeq/_version.py
MutSeq-1.0.1.dist-info/LICENSE
MutSeq-1.0.1.dist-info/METADATA
MutSeq-1.0.1.dist-info/WHEEL
MutSeq-1.0.1.dist-info/entry_points.txt
MutSeq-1.0.1.dist-info/top_level.txt
MutSeq-1.0.1.dist-info/RECORD
